<?xml version="1.0" encoding="utf-8"?>
<Table xmlns:i="http://www.w3.org/2001/XMLSchema-instance" xmlns="http://schemas.ntreev.com">
  <Columns>
    <Item>Type</Item>
    <Item>Name</Item>
    <Item>Comment</Item>
    <Item>Value</Item>
    <Item>ko_KR</Item>
  </Columns>
  <Rows>
    <Row>
      <IsEnabled>true</IsEnabled>
      <ModificationInfo>
        <DateTime>2017-10-31T06:53:14.3731938Z</DateTime>
        <ID></ID>
      </ModificationInfo>
      <Tags>All</Tags>
      <Values>
        <Item>Button</Item>
        <Item>Cancel</Item>
        <Item i:nil="true" />
        <Item>_Cancel</Item>
        <Item>취소(_C)</Item>
      </Values>
    </Row>
    <Row>
      <IsEnabled>true</IsEnabled>
      <ModificationInfo>
        <DateTime>2017-10-31T06:53:14.3731938Z</DateTime>
        <ID></ID>
      </ModificationInfo>
      <Tags>All</Tags>
      <Values>
        <Item>Button</Item>
        <Item>OK</Item>
        <Item i:nil="true" />
        <Item>_OK</Item>
        <Item>확인(_O)</Item>
      </Values>
    </Row>
    <Row>
      <IsEnabled>true</IsEnabled>
      <ModificationInfo>
        <DateTime>2017-10-31T06:53:14.3731938Z</DateTime>
        <ID></ID>
      </ModificationInfo>
      <Tags>All</Tags>
      <Values>
        <Item>Comment</Item>
        <Item>IsMember</Item>
        <Item i:nil="true" />
        <Item>Whether or not he is involved in editing</Item>
        <Item>자신이 편집에 참여하고 있는지에 대한 여부</Item>
      </Values>
    </Row>
    <Row>
      <IsEnabled>true</IsEnabled>
      <ModificationInfo>
        <DateTime>2017-10-31T06:53:14.3731938Z</DateTime>
        <ID></ID>
      </ModificationInfo>
      <Tags>All</Tags>
      <Values>
        <Item>Label</Item>
        <Item>CaseSensitive</Item>
        <Item i:nil="true" />
        <Item>Case sensitive</Item>
        <Item>대소문자 구분</Item>
      </Values>
    </Row>
    <Row>
      <IsEnabled>true</IsEnabled>
      <ModificationInfo>
        <DateTime>2017-10-31T06:53:14.3731938Z</DateTime>
        <ID></ID>
      </ModificationInfo>
      <Tags>All</Tags>
      <Values>
        <Item>Label</Item>
        <Item>Name</Item>
        <Item i:nil="true" />
        <Item>Name</Item>
        <Item>이름</Item>
      </Values>
    </Row>
    <Row>
      <IsEnabled>true</IsEnabled>
      <ModificationInfo>
        <DateTime>2017-10-31T06:53:14.3731938Z</DateTime>
        <ID></ID>
      </ModificationInfo>
      <Tags>All</Tags>
      <Values>
        <Item>Label</Item>
        <Item>Rule</Item>
        <Item i:nil="true" />
        <Item>Rules</Item>
        <Item>규칙</Item>
      </Values>
    </Row>
    <Row>
      <IsEnabled>true</IsEnabled>
      <ModificationInfo>
        <DateTime>2017-10-31T06:53:14.3731938Z</DateTime>
        <ID></ID>
      </ModificationInfo>
      <Tags>All</Tags>
      <Values>
        <Item>Label</Item>
        <Item>StringtoCompare</Item>
        <Item i:nil="true" />
        <Item>String to compare</Item>
        <Item>비교 문자열</Item>
      </Values>
    </Row>
    <Row>
      <IsEnabled>true</IsEnabled>
      <ModificationInfo>
        <DateTime>2017-10-31T06:53:14.3731938Z</DateTime>
        <ID></ID>
      </ModificationInfo>
      <Tags>All</Tags>
      <Values>
        <Item>Label</Item>
        <Item>UseGlobPattern</Item>
        <Item i:nil="true" />
        <Item>Use glob pattern</Item>
        <Item>Glob 패턴 사용</Item>
      </Values>
    </Row>
    <Row>
      <IsEnabled>true</IsEnabled>
      <ModificationInfo>
        <DateTime>2017-10-31T06:53:14.3731938Z</DateTime>
        <ID></ID>
      </ModificationInfo>
      <Tags>All</Tags>
      <Values>
        <Item>MenuItem</Item>
        <Item>AddToBookmark</Item>
        <Item i:nil="true" />
        <Item>Add to bookmark</Item>
        <Item>즐겨찾기 설정</Item>
      </Values>
    </Row>
    <Row>
      <IsEnabled>true</IsEnabled>
      <ModificationInfo>
        <DateTime>2017-10-31T06:53:14.3731938Z</DateTime>
        <ID></ID>
      </ModificationInfo>
      <Tags>All</Tags>
      <Values>
        <Item>MenuItem</Item>
        <Item>CopyList</Item>
        <Item i:nil="true" />
        <Item>Copy to clipboard</Item>
        <Item>목록 복사하기</Item>
      </Values>
    </Row>
    <Row>
      <IsEnabled>true</IsEnabled>
      <ModificationInfo>
        <DateTime>2017-10-31T06:53:14.3731938Z</DateTime>
        <ID></ID>
      </ModificationInfo>
      <Tags>All</Tags>
      <Values>
        <Item>MenuItem</Item>
        <Item>Delete</Item>
        <Item i:nil="true" />
        <Item>_Delete</Item>
        <Item>삭제(_D)</Item>
      </Values>
    </Row>
    <Row>
      <IsEnabled>true</IsEnabled>
      <ModificationInfo>
        <DateTime>2017-10-31T06:53:14.3741945Z</DateTime>
        <ID></ID>
      </ModificationInfo>
      <Tags>All</Tags>
      <Values>
        <Item>MenuItem</Item>
        <Item>Edit</Item>
        <Item i:nil="true" />
        <Item>_Edit</Item>
        <Item>편집(_E)</Item>
      </Values>
    </Row>
    <Row>
      <IsEnabled>true</IsEnabled>
      <ModificationInfo>
        <DateTime>2017-10-31T06:53:14.3741945Z</DateTime>
        <ID></ID>
      </ModificationInfo>
      <Tags>All</Tags>
      <Values>
        <Item>MenuItem</Item>
        <Item>NewFolder</Item>
        <Item i:nil="true" />
        <Item>_New Folder</Item>
        <Item>새 폴더(_N)...</Item>
      </Values>
    </Row>
    <Row>
      <IsEnabled>true</IsEnabled>
      <ModificationInfo>
        <DateTime>2017-10-31T06:53:14.3741945Z</DateTime>
        <ID></ID>
      </ModificationInfo>
      <Tags>All</Tags>
      <Values>
        <Item>MenuItem</Item>
        <Item>NewSmartSet</Item>
        <Item i:nil="true" />
        <Item>_New SmartSet</Item>
        <Item>새 스마트 세트(_T)...</Item>
      </Values>
    </Row>
    <Row>
      <IsEnabled>true</IsEnabled>
      <ModificationInfo>
        <DateTime>2017-10-31T06:53:14.3741945Z</DateTime>
        <ID></ID>
      </ModificationInfo>
      <Tags>All</Tags>
      <Values>
        <Item>MenuItem</Item>
        <Item>RemoveFromBookmark</Item>
        <Item i:nil="true" />
        <Item>Remove from bookmark</Item>
        <Item>즐겨찾기 해제</Item>
      </Values>
    </Row>
    <Row>
      <IsEnabled>true</IsEnabled>
      <ModificationInfo>
        <DateTime>2017-10-31T06:53:14.3741945Z</DateTime>
        <ID></ID>
      </ModificationInfo>
      <Tags>All</Tags>
      <Values>
        <Item>MenuItem</Item>
        <Item>Rename</Item>
        <Item i:nil="true" />
        <Item>_Rename</Item>
        <Item>이름변경(_R)</Item>
      </Values>
    </Row>
    <Row>
      <IsEnabled>true</IsEnabled>
      <ModificationInfo>
        <DateTime>2017-10-31T06:53:14.3741945Z</DateTime>
        <ID></ID>
      </ModificationInfo>
      <Tags>All</Tags>
      <Values>
        <Item>Text</Item>
        <Item>BaseTable</Item>
        <Item i:nil="true" />
        <Item>Base Table</Item>
        <Item>기본 테이블</Item>
      </Values>
    </Row>
    <Row>
      <IsEnabled>true</IsEnabled>
      <ModificationInfo>
        <DateTime>2017-10-31T06:53:14.3741945Z</DateTime>
        <ID></ID>
      </ModificationInfo>
      <Tags>All</Tags>
      <Values>
        <Item>Text</Item>
        <Item>ChildTable</Item>
        <Item i:nil="true" />
        <Item>Child Table</Item>
        <Item>자식 테이블</Item>
      </Values>
    </Row>
    <Row>
      <IsEnabled>true</IsEnabled>
      <ModificationInfo>
        <DateTime>2017-10-31T06:53:14.3741945Z</DateTime>
        <ID></ID>
      </ModificationInfo>
      <Tags>All</Tags>
      <Values>
        <Item>Text</Item>
        <Item>DerivedTable</Item>
        <Item i:nil="true" />
        <Item>Derived Table</Item>
        <Item>상속된 테이블</Item>
      </Values>
    </Row>
    <Row>
      <IsEnabled>true</IsEnabled>
      <ModificationInfo>
        <DateTime>2017-10-31T06:53:14.3741945Z</DateTime>
        <ID></ID>
      </ModificationInfo>
      <Tags>All</Tags>
      <Values>
        <Item>Text</Item>
        <Item>IsBeingEdited</Item>
        <Item i:nil="true" />
        <Item>Is Being Edited</Item>
        <Item>편집중</Item>
      </Values>
    </Row>
    <Row>
      <IsEnabled>true</IsEnabled>
      <ModificationInfo>
        <DateTime>2017-10-31T06:53:14.3741945Z</DateTime>
        <ID></ID>
      </ModificationInfo>
      <Tags>All</Tags>
      <Values>
        <Item>Text</Item>
        <Item>IsBeingSetup</Item>
        <Item i:nil="true" />
        <Item>Is Begin Setup</Item>
        <Item>형태 편집중</Item>
      </Values>
    </Row>
    <Row>
      <IsEnabled>true</IsEnabled>
      <ModificationInfo>
        <DateTime>2017-10-31T06:53:14.3741945Z</DateTime>
        <ID></ID>
      </ModificationInfo>
      <Tags>All</Tags>
      <Values>
        <Item>Text</Item>
        <Item>IsFlag</Item>
        <Item i:nil="true" />
        <Item>Is Flag</Item>
        <Item>플래그 집합</Item>
      </Values>
    </Row>
    <Row>
      <IsEnabled>true</IsEnabled>
      <ModificationInfo>
        <DateTime>2017-10-31T06:53:14.3751952Z</DateTime>
        <ID></ID>
      </ModificationInfo>
      <Tags>All</Tags>
      <Values>
        <Item>Text</Item>
        <Item>IsMember</Item>
        <Item i:nil="true" />
        <Item>Is Member</Item>
        <Item>편집 참여여부</Item>
      </Values>
    </Row>
    <Row>
      <IsEnabled>true</IsEnabled>
      <ModificationInfo>
        <DateTime>2017-10-31T06:53:14.3751952Z</DateTime>
        <ID></ID>
      </ModificationInfo>
      <Tags>All</Tags>
      <Values>
        <Item>Text</Item>
        <Item>None</Item>
        <Item i:nil="true" />
        <Item>None</Item>
        <Item>없음</Item>
      </Values>
    </Row>
    <Row>
      <IsEnabled>true</IsEnabled>
      <ModificationInfo>
        <DateTime>2017-10-31T06:53:14.3751952Z</DateTime>
        <ID></ID>
      </ModificationInfo>
      <Tags>All</Tags>
      <Values>
        <Item>Text</Item>
        <Item>Now</Item>
        <Item i:nil="true" />
        <Item>Now</Item>
        <Item>지금</Item>
      </Values>
    </Row>
    <Row>
      <IsEnabled>true</IsEnabled>
      <ModificationInfo>
        <DateTime>2017-10-31T06:53:14.3751952Z</DateTime>
        <ID></ID>
      </ModificationInfo>
      <Tags>All</Tags>
      <Values>
        <Item>Text</Item>
        <Item>SpecificTime</Item>
        <Item i:nil="true" />
        <Item>Specific time</Item>
        <Item>특정 시간</Item>
      </Values>
    </Row>
    <Row>
      <IsEnabled>true</IsEnabled>
      <ModificationInfo>
        <DateTime>2017-10-31T06:53:14.3751952Z</DateTime>
        <ID></ID>
      </ModificationInfo>
      <Tags>All</Tags>
      <Values>
        <Item>Text</Item>
        <Item>Today</Item>
        <Item i:nil="true" />
        <Item>Today</Item>
        <Item>오늘</Item>
      </Values>
    </Row>
    <Row>
      <IsEnabled>true</IsEnabled>
      <ModificationInfo>
        <DateTime>2017-10-31T06:53:14.3751952Z</DateTime>
        <ID></ID>
      </ModificationInfo>
      <Tags>All</Tags>
      <Values>
        <Item>Title</Item>
        <Item>Bookmark</Item>
        <Item i:nil="true" />
        <Item>Bookmark</Item>
        <Item>즐겨 찾기</Item>
      </Values>
    </Row>
    <Row>
      <IsEnabled>true</IsEnabled>
      <ModificationInfo>
        <DateTime>2017-10-31T06:53:14.3751952Z</DateTime>
        <ID></ID>
      </ModificationInfo>
      <Tags>All</Tags>
      <Values>
        <Item>Title</Item>
        <Item>ColumnCount</Item>
        <Item i:nil="true" />
        <Item>Column Count</Item>
        <Item>컬럼 갯수</Item>
      </Values>
    </Row>
    <Row>
      <IsEnabled>true</IsEnabled>
      <ModificationInfo>
        <DateTime>2017-10-31T06:53:14.3751952Z</DateTime>
        <ID></ID>
      </ModificationInfo>
      <Tags>All</Tags>
      <Values>
        <Item>Title</Item>
        <Item>ColumnDataType</Item>
        <Item i:nil="true" />
        <Item>Column DataType</Item>
        <Item>컬럼 데이터 타입</Item>
      </Values>
    </Row>
    <Row>
      <IsEnabled>true</IsEnabled>
      <ModificationInfo>
        <DateTime>2017-10-31T06:53:14.3751952Z</DateTime>
        <ID></ID>
      </ModificationInfo>
      <Tags>All</Tags>
      <Values>
        <Item>Title</Item>
        <Item>ColumnName</Item>
        <Item i:nil="true" />
        <Item>Column Name</Item>
        <Item>컬럼 이름</Item>
      </Values>
    </Row>
    <Row>
      <IsEnabled>true</IsEnabled>
      <ModificationInfo>
        <DateTime>2017-10-31T06:53:14.3751952Z</DateTime>
        <ID></ID>
      </ModificationInfo>
      <Tags>All</Tags>
      <Values>
        <Item>Title</Item>
        <Item>DateTime</Item>
        <Item i:nil="true" />
        <Item>DateTime</Item>
        <Item>기간</Item>
      </Values>
    </Row>
    <Row>
      <IsEnabled>true</IsEnabled>
      <ModificationInfo>
        <DateTime>2017-10-31T06:53:14.3761959Z</DateTime>
        <ID></ID>
      </ModificationInfo>
      <Tags>All</Tags>
      <Values>
        <Item>Title</Item>
        <Item>EditSmartCollection</Item>
        <Item i:nil="true" />
        <Item>Edit Smart Collection</Item>
        <Item>스마트 컬렉션 편집</Item>
      </Values>
    </Row>
    <Row>
      <IsEnabled>true</IsEnabled>
      <ModificationInfo>
        <DateTime>2017-10-31T06:53:14.3761959Z</DateTime>
        <ID></ID>
      </ModificationInfo>
      <Tags>All</Tags>
      <Values>
        <Item>Title</Item>
        <Item>KeyCount</Item>
        <Item i:nil="true" />
        <Item>Key Count</Item>
        <Item>키 갯수</Item>
      </Values>
    </Row>
    <Row>
      <IsEnabled>true</IsEnabled>
      <ModificationInfo>
        <DateTime>2017-10-31T06:53:14.3761959Z</DateTime>
        <ID></ID>
      </ModificationInfo>
      <Tags>All</Tags>
      <Values>
        <Item>Title</Item>
        <Item>NewSmartCollection</Item>
        <Item i:nil="true" />
        <Item>New Smart Collection</Item>
        <Item>스마트 컬렉션 추가</Item>
      </Values>
    </Row>
    <Row>
      <IsEnabled>true</IsEnabled>
      <ModificationInfo>
        <DateTime>2017-10-31T06:53:14.3761959Z</DateTime>
        <ID></ID>
      </ModificationInfo>
      <Tags>All</Tags>
      <Values>
        <Item>Title</Item>
        <Item>SmartSet</Item>
        <Item i:nil="true" />
        <Item>SmartSet</Item>
        <Item>스마트 세트</Item>
      </Values>
    </Row>
    <Row>
      <IsEnabled>true</IsEnabled>
      <ModificationInfo>
        <DateTime>2017-10-31T06:53:14.3761959Z</DateTime>
        <ID></ID>
      </ModificationInfo>
      <Tags>All</Tags>
      <Values>
        <Item>Title</Item>
        <Item>TableAttributes</Item>
        <Item i:nil="true" />
        <Item>Table Attributes</Item>
        <Item>테이블 특성</Item>
      </Values>
    </Row>
    <Row>
      <IsEnabled>true</IsEnabled>
      <ModificationInfo>
        <DateTime>2017-10-31T06:53:14.3761959Z</DateTime>
        <ID></ID>
      </ModificationInfo>
      <Tags>All</Tags>
      <Values>
        <Item>Title</Item>
        <Item>TableContentModifiedDateTime</Item>
        <Item i:nil="true" />
        <Item>Table Content Modified DateTime</Item>
        <Item>테이블 내용 변경일자</Item>
      </Values>
    </Row>
    <Row>
      <IsEnabled>true</IsEnabled>
      <ModificationInfo>
        <DateTime>2017-10-31T06:53:14.3761959Z</DateTime>
        <ID></ID>
      </ModificationInfo>
      <Tags>All</Tags>
      <Values>
        <Item>Title</Item>
        <Item>TableContentModifier</Item>
        <Item i:nil="true" />
        <Item>Table Content Modifier</Item>
        <Item>테이블 내용 변경자</Item>
      </Values>
    </Row>
    <Row>
      <IsEnabled>true</IsEnabled>
      <ModificationInfo>
        <DateTime>2017-10-31T06:53:14.3761959Z</DateTime>
        <ID></ID>
      </ModificationInfo>
      <Tags>All</Tags>
      <Values>
        <Item>Title</Item>
        <Item>TableCreatedDateTime</Item>
        <Item i:nil="true" />
        <Item>Table Created DateTime</Item>
        <Item>테이블 생성일자</Item>
      </Values>
    </Row>
    <Row>
      <IsEnabled>true</IsEnabled>
      <ModificationInfo>
        <DateTime>2017-10-31T06:53:14.3761959Z</DateTime>
        <ID></ID>
      </ModificationInfo>
      <Tags>All</Tags>
      <Values>
        <Item>Title</Item>
        <Item>TableCreatedUser</Item>
        <Item i:nil="true" />
        <Item>Table Creator</Item>
        <Item>테이블 생성자</Item>
      </Values>
    </Row>
    <Row>
      <IsEnabled>true</IsEnabled>
      <ModificationInfo>
        <DateTime>2017-10-31T06:53:14.3771966Z</DateTime>
        <ID></ID>
      </ModificationInfo>
      <Tags>All</Tags>
      <Values>
        <Item>Title</Item>
        <Item>TableIsLocked</Item>
        <Item i:nil="true" />
        <Item>Table Is Locked</Item>
        <Item>테이블 잠김 여부</Item>
      </Values>
    </Row>
    <Row>
      <IsEnabled>true</IsEnabled>
      <ModificationInfo>
        <DateTime>2017-10-31T06:53:14.3771966Z</DateTime>
        <ID></ID>
      </ModificationInfo>
      <Tags>All</Tags>
      <Values>
        <Item>Title</Item>
        <Item>TableName</Item>
        <Item i:nil="true" />
        <Item>Table Name</Item>
        <Item>테이블 이름</Item>
      </Values>
    </Row>
    <Row>
      <IsEnabled>true</IsEnabled>
      <ModificationInfo>
        <DateTime>2017-10-31T06:53:14.3771966Z</DateTime>
        <ID></ID>
      </ModificationInfo>
      <Tags>All</Tags>
      <Values>
        <Item>Title</Item>
        <Item>TableSmartCollection</Item>
        <Item i:nil="true" />
        <Item>Table Smart Collection</Item>
        <Item>테이블 스마트 컬렉션</Item>
      </Values>
    </Row>
    <Row>
      <IsEnabled>true</IsEnabled>
      <ModificationInfo>
        <DateTime>2017-10-31T06:53:14.3771966Z</DateTime>
        <ID></ID>
      </ModificationInfo>
      <Tags>All</Tags>
      <Values>
        <Item>Title</Item>
        <Item>TableStates</Item>
        <Item i:nil="true" />
        <Item>Table States</Item>
        <Item>테이블 상태</Item>
      </Values>
    </Row>
    <Row>
      <IsEnabled>true</IsEnabled>
      <ModificationInfo>
        <DateTime>2017-10-31T06:53:14.3771966Z</DateTime>
        <ID></ID>
      </ModificationInfo>
      <Tags>All</Tags>
      <Values>
        <Item>Title</Item>
        <Item>TableTags</Item>
        <Item i:nil="true" />
        <Item>Table Tags</Item>
        <Item>테이블 태그</Item>
      </Values>
    </Row>
    <Row>
      <IsEnabled>true</IsEnabled>
      <ModificationInfo>
        <DateTime>2017-10-31T06:53:14.3771966Z</DateTime>
        <ID></ID>
      </ModificationInfo>
      <Tags>All</Tags>
      <Values>
        <Item>Title</Item>
        <Item>TableTemplateModifiedDateTime</Item>
        <Item i:nil="true" />
        <Item>Table Template Modified DateTime</Item>
        <Item>테이블 형태 변경일자</Item>
      </Values>
    </Row>
    <Row>
      <IsEnabled>true</IsEnabled>
      <ModificationInfo>
        <DateTime>2017-10-31T06:53:14.3771966Z</DateTime>
        <ID></ID>
      </ModificationInfo>
      <Tags>All</Tags>
      <Values>
        <Item>Title</Item>
        <Item>TableTemplateModifier</Item>
        <Item i:nil="true" />
        <Item>Table Template Modifier</Item>
        <Item>테이블 형태 변경자</Item>
      </Values>
    </Row>
    <Row>
      <IsEnabled>true</IsEnabled>
      <ModificationInfo>
        <DateTime>2017-10-31T06:53:14.3771966Z</DateTime>
        <ID></ID>
      </ModificationInfo>
      <Tags>All</Tags>
      <Values>
        <Item>Title</Item>
        <Item>Tags</Item>
        <Item i:nil="true" />
        <Item>Tags</Item>
        <Item>태그</Item>
      </Values>
    </Row>
    <Row>
      <IsEnabled>true</IsEnabled>
      <ModificationInfo>
        <DateTime>2017-10-31T06:53:14.3771966Z</DateTime>
        <ID></ID>
      </ModificationInfo>
      <Tags>All</Tags>
      <Values>
        <Item>Title</Item>
        <Item>TypeAttributes</Item>
        <Item i:nil="true" />
        <Item>Type Attributes</Item>
        <Item>타입 특성</Item>
      </Values>
    </Row>
    <Row>
      <IsEnabled>true</IsEnabled>
      <ModificationInfo>
        <DateTime>2017-10-31T06:53:14.3781973Z</DateTime>
        <ID></ID>
      </ModificationInfo>
      <Tags>All</Tags>
      <Values>
        <Item>Title</Item>
        <Item>TypeCreatedDateTime</Item>
        <Item i:nil="true" />
        <Item>Type Created DateTime</Item>
        <Item>타입 생성 일자</Item>
      </Values>
    </Row>
    <Row>
      <IsEnabled>true</IsEnabled>
      <ModificationInfo>
        <DateTime>2017-10-31T06:53:14.3781973Z</DateTime>
        <ID></ID>
      </ModificationInfo>
      <Tags>All</Tags>
      <Values>
        <Item>Title</Item>
        <Item>TypeCreator</Item>
        <Item i:nil="true" />
        <Item>Type Creator</Item>
        <Item>타입 생성자</Item>
      </Values>
    </Row>
    <Row>
      <IsEnabled>true</IsEnabled>
      <ModificationInfo>
        <DateTime>2017-10-31T06:53:14.3781973Z</DateTime>
        <ID></ID>
      </ModificationInfo>
      <Tags>All</Tags>
      <Values>
        <Item>Title</Item>
        <Item>TypeModifiedDateTime</Item>
        <Item i:nil="true" />
        <Item>Type Modified DateTime</Item>
        <Item>타입 변경 일자</Item>
      </Values>
    </Row>
    <Row>
      <IsEnabled>true</IsEnabled>
      <ModificationInfo>
        <DateTime>2017-10-31T06:53:14.3781973Z</DateTime>
        <ID></ID>
      </ModificationInfo>
      <Tags>All</Tags>
      <Values>
        <Item>Title</Item>
        <Item>TypeModifier</Item>
        <Item i:nil="true" />
        <Item>Type Modifier</Item>
        <Item>타입 변경자</Item>
      </Values>
    </Row>
    <Row>
      <IsEnabled>true</IsEnabled>
      <ModificationInfo>
        <DateTime>2017-10-31T06:53:14.3781973Z</DateTime>
        <ID></ID>
      </ModificationInfo>
      <Tags>All</Tags>
      <Values>
        <Item>Title</Item>
        <Item>TypeName</Item>
        <Item i:nil="true" />
        <Item>Type Name</Item>
        <Item>타입 이름</Item>
      </Values>
    </Row>
    <Row>
      <IsEnabled>true</IsEnabled>
      <ModificationInfo>
        <DateTime>2017-10-31T06:53:14.3781973Z</DateTime>
        <ID></ID>
      </ModificationInfo>
      <Tags>All</Tags>
      <Values>
        <Item>Title</Item>
        <Item>TypeSmartCollection</Item>
        <Item i:nil="true" />
        <Item>Type Smart Collection</Item>
        <Item>타입 스마트 컬렉션</Item>
      </Values>
    </Row>
    <Row>
      <IsEnabled>true</IsEnabled>
      <ModificationInfo>
        <DateTime>2017-10-31T06:53:14.3781973Z</DateTime>
        <ID></ID>
      </ModificationInfo>
      <Tags>All</Tags>
      <Values>
        <Item>Title</Item>
        <Item>TypeState</Item>
        <Item i:nil="true" />
        <Item>Type States</Item>
        <Item>타입 상태</Item>
      </Values>
    </Row>
    <Row>
      <IsEnabled>true</IsEnabled>
      <ModificationInfo>
        <DateTime>2018-03-19T05:35:16.2964518Z</DateTime>
        <ID>s2quake</ID>
      </ModificationInfo>
      <Tags>All</Tags>
      <Values>
        <Item>Label</Item>
        <Item>ItemName</Item>
        <Item i:nil="true" />
        <Item>Item Name</Item>
        <Item>아이템 이름</Item>
      </Values>
    </Row>
    <Row>
      <IsEnabled>true</IsEnabled>
      <ModificationInfo>
        <DateTime>2018-03-19T05:48:25.1898374Z</DateTime>
        <ID>s2quake</ID>
      </ModificationInfo>
      <Tags>All</Tags>
      <Values>
        <Item>Button</Item>
        <Item>Add</Item>
        <Item i:nil="true" />
        <Item>_Add</Item>
        <Item>추가(_A)</Item>
      </Values>
    </Row>
    <Row>
      <IsEnabled>true</IsEnabled>
      <ModificationInfo>
        <DateTime>2018-01-02T01:51:15.3441969Z</DateTime>
        <ID>admin</ID>
      </ModificationInfo>
      <Tags>All</Tags>
      <Values>
        <Item>Button</Item>
        <Item>Close</Item>
        <Item i:nil="true" />
        <Item>_Close</Item>
        <Item>닫기(_C)</Item>
      </Values>
    </Row>
    <Row>
      <IsEnabled>true</IsEnabled>
      <ModificationInfo>
        <DateTime>2018-01-02T02:45:46.6075426Z</DateTime>
        <ID>admin</ID>
      </ModificationInfo>
      <Tags>All</Tags>
      <Values>
        <Item>Title</Item>
        <Item>AddBookmark</Item>
        <Item i:nil="true" />
        <Item>Add Bookmark</Item>
        <Item>즐겨 찾기에 추가</Item>
      </Values>
    </Row>
    <Row>
      <IsEnabled>true</IsEnabled>
      <ModificationInfo>
        <DateTime>2018-01-02T04:37:26.1017096Z</DateTime>
        <ID>admin</ID>
      </ModificationInfo>
      <Tags>All</Tags>
      <Values>
        <Item>Label</Item>
        <Item>TableName</Item>
        <Item i:nil="true" />
        <Item>Table Name</Item>
        <Item>테이블 이름</Item>
      </Values>
    </Row>
    <Row>
      <IsEnabled>true</IsEnabled>
      <ModificationInfo>
        <DateTime>2018-01-03T02:05:16.3914277Z</DateTime>
        <ID>admin</ID>
      </ModificationInfo>
      <Tags>All</Tags>
      <Values>
        <Item>MenuItem</Item>
        <Item>Move</Item>
        <Item i:nil="true" />
        <Item>_Move</Item>
        <Item>이동(_M)</Item>
      </Values>
    </Row>
    <Row>
      <IsEnabled>true</IsEnabled>
      <ModificationInfo>
        <DateTime>2018-01-04T00:43:24.3669538Z</DateTime>
        <ID>admin</ID>
      </ModificationInfo>
      <Tags>All</Tags>
      <Values>
        <Item>Button</Item>
        <Item>Move</Item>
        <Item i:nil="true" />
        <Item>_Move</Item>
        <Item>이동(_M)</Item>
      </Values>
    </Row>
    <Row>
      <IsEnabled>true</IsEnabled>
      <ModificationInfo>
        <DateTime>2018-01-04T04:12:17.2729667Z</DateTime>
        <ID>admin</ID>
      </ModificationInfo>
      <Tags>All</Tags>
      <Values>
        <Item>Label</Item>
        <Item>CurrentPath</Item>
        <Item i:nil="true" />
        <Item>Current Path</Item>
        <Item>현재 경로</Item>
      </Values>
    </Row>
    <Row>
      <IsEnabled>true</IsEnabled>
      <ModificationInfo>
        <DateTime>2018-01-04T04:18:56.2280674Z</DateTime>
        <ID>admin</ID>
      </ModificationInfo>
      <Tags>All</Tags>
      <Values>
        <Item>Title</Item>
        <Item>MoveBookmark</Item>
        <Item i:nil="true" />
        <Item>Move Bookmark</Item>
        <Item>즐겨 찾기 이동</Item>
      </Values>
    </Row>
    <Row>
      <IsEnabled>true</IsEnabled>
      <ModificationInfo>
        <DateTime>2018-01-04T04:33:00.2519499Z</DateTime>
        <ID>admin</ID>
      </ModificationInfo>
      <Tags>All</Tags>
      <Values>
        <Item>MenuItem</Item>
        <Item>MoveBookmark</Item>
        <Item i:nil="true" />
        <Item>Move Bookmark</Item>
        <Item>즐겨찾기 이동</Item>
      </Values>
    </Row>
    <Row>
      <IsEnabled>true</IsEnabled>
      <ModificationInfo>
        <DateTime>2018-01-05T02:33:55.8011549Z</DateTime>
        <ID>admin</ID>
      </ModificationInfo>
      <Tags>All</Tags>
      <Values>
        <Item>Label</Item>
        <Item>FolderName</Item>
        <Item i:nil="true" />
        <Item>Folder Name</Item>
        <Item>폴더 이름</Item>
      </Values>
    </Row>
    <Row>
      <IsEnabled>true</IsEnabled>
      <ModificationInfo>
        <DateTime>2018-01-09T01:35:30.1085371Z</DateTime>
        <ID>admin</ID>
      </ModificationInfo>
      <Tags>All</Tags>
      <Values>
        <Item>Title</Item>
        <Item>NewCategory</Item>
        <Item i:nil="true" />
        <Item>New Category</Item>
        <Item>새 폴더</Item>
      </Values>
    </Row>
    <Row>
      <IsEnabled>true</IsEnabled>
      <ModificationInfo>
        <DateTime>2018-01-09T02:02:30.3741829Z</DateTime>
        <ID>admin</ID>
      </ModificationInfo>
      <Tags>All</Tags>
      <Values>
        <Item>Label</Item>
        <Item>CategoryPath</Item>
        <Item i:nil="true" />
        <Item>Folder Path</Item>
        <Item>폴더 경로</Item>
      </Values>
    </Row>
    <Row>
      <IsEnabled>true</IsEnabled>
      <ModificationInfo>
        <DateTime>2018-01-09T02:02:48.8758154Z</DateTime>
        <ID>admin</ID>
      </ModificationInfo>
      <Tags>All</Tags>
      <Values>
        <Item>Label</Item>
        <Item>CategoryName</Item>
        <Item i:nil="true" />
        <Item>Folder Name</Item>
        <Item>폴더 이름</Item>
      </Values>
    </Row>
    <Row>
      <IsEnabled>true</IsEnabled>
      <ModificationInfo>
        <DateTime>2018-01-09T02:03:08.4070497Z</DateTime>
        <ID>admin</ID>
      </ModificationInfo>
      <Tags>All</Tags>
      <Values>
        <Item>Button</Item>
        <Item>Create</Item>
        <Item i:nil="true" />
        <Item>Cre_ate</Item>
        <Item>생성(_O)</Item>
      </Values>
    </Row>
    <Row>
      <IsEnabled>true</IsEnabled>
      <ModificationInfo>
        <DateTime>2018-03-19T05:45:02.7794819Z</DateTime>
        <ID>s2quake</ID>
      </ModificationInfo>
      <Tags>All</Tags>
      <Values>
        <Item>Label</Item>
        <Item>TargetPath</Item>
        <Item i:nil="true" />
        <Item>Target Path</Item>
        <Item>대상 폴더</Item>
      </Values>
    </Row>
  </Rows>
</Table>